application/__init__.py
application/application_brutta.py
database/__init__.py
database/firebase.py
provapipeline2023-0.1.1.dist-info/METADATA
provapipeline2023-0.1.1.dist-info/WHEEL
provapipeline2023-0.1.1.dist-info/top_level.txt
provapipeline2023-0.1.1.dist-info/RECORD
