Metadata-Version: 2.1
Name: provapipeline2023
Version: 0.1.1
Summary: Some Python package
Author: Me
Author-email: me@example.com
License: MIT
